{
  "input-otp": {
    "gap": {
      "value": "{inline.s}",
      "type": "dimension",
      "description": "Gap between input cells"
    },
    "cell": {
      "size": {
        "value": "48px",
        "type": "dimension",
        "description": "Cell width and height"
      },
      "fontSize": {
        "value": "20px",
        "type": "dimension",
        "description": "Cell character font size"
      },
      "fontWeight": {
        "value": "600",
        "type": "fontWeight",
        "description": "Cell character font weight"
      },
      "radius": {
        "value": "{radius.default}",
        "type": "dimension",
        "description": "Cell border radius"
      },
      "background": {
        "default": {
          "value": "{surface.canvas}",
          "type": "color",
          "description": "Default cell background"
        },
        "focus": {
          "value": "{surface.canvas}",
          "type": "color",
          "description": "Focused cell background"
        },
        "filled": {
          "value": "{neutral.50}",
          "type": "color",
          "description": "Filled cell background"
        },
        "disabled": {
          "value": "{neutral.100}",
          "type": "color",
          "description": "Disabled cell background"
        }
      },
      "border": {
        "width": {
          "value": "1px",
          "type": "dimension",
          "description": "Cell border width"
        },
        "color": {
          "default": {
            "value": "{neutral.300}",
            "type": "color",
            "description": "Default cell border color"
          },
          "hover": {
            "value": "{neutral.400}",
            "type": "color",
            "description": "Hover cell border color"
          },
          "focus": {
            "value": "{brand.primary}",
            "type": "color",
            "description": "Focused cell border color"
          },
          "filled": {
            "value": "{neutral.400}",
            "type": "color",
            "description": "Filled cell border color"
          },
          "disabled": {
            "value": "{neutral.200}",
            "type": "color",
            "description": "Disabled cell border color"
          },
          "error": {
            "value": "{feedback.error}",
            "type": "color",
            "description": "Error cell border color"
          }
        }
      },
      "text": {
        "default": {
          "value": "{text.default}",
          "type": "color",
          "description": "Default text color"
        },
        "disabled": {
          "value": "{text.muted}",
          "type": "color",
          "description": "Disabled text color"
        },
        "mask": {
          "value": "{text.default}",
          "type": "color",
          "description": "Masked character color"
        }
      }
    },
    "focus": {
      "ringWidth": {
        "value": "2px",
        "type": "dimension",
        "description": "Focus ring width"
      },
      "ringColor": {
        "value": "{focus.ring}",
        "type": "color",
        "description": "Focus ring color"
      },
      "ringOffset": {
        "value": "1px",
        "type": "dimension",
        "description": "Focus ring offset"
      }
    },
    "separator": {
      "width": {
        "value": "8px",
        "type": "dimension",
        "description": "Separator dash width"
      },
      "color": {
        "value": "{neutral.400}",
        "type": "color",
        "description": "Separator color"
      }
    }
  }
}
